radicli/__init__.py
radicli/cli.py
radicli/document.py
radicli/parser.py
radicli/py.typed
radicli/static.py
radicli/util.py
radicli/tests/__init__.py
radicli/tests/test_cli.py
radicli/tests/test_document.py
radicli/tests/test_parser.py
radicli/tests/test_util.py
radicli-0.0.26.dist-info/licenses/LICENSE
radicli-0.0.26.dist-info/METADATA
radicli-0.0.26.dist-info/WHEEL
radicli-0.0.26.dist-info/top_level.txt
radicli-0.0.26.dist-info/zip-safe
radicli-0.0.26.dist-info/RECORD
